fonts/__init__.py
fonts/fonts/__init__.py
fonts/otf/__init__.py
fonts/ttf/__init__.py
fonts-0.0.3.dist-info/DESCRIPTION.rst
fonts-0.0.3.dist-info/METADATA
fonts-0.0.3.dist-info/RECORD
fonts-0.0.3.dist-info/WHEEL
fonts-0.0.3.dist-info/metadata.json
fonts-0.0.3.dist-info/top_level.txt
