Metadata-Version: 1.1
Name: fonts
Version: 0.0.3
Summary: Python Fonts
Home-page: https://github.com/pimoroni/fonts-python
Author: Philip Howard
Author-email: phil@pimoroni.com
License: MIT, OFL
Keywords: Fonts
Platform: UNKNOWN
Classifier: Development Status :: 5 - Production/Stable
Classifier: Operating System :: POSIX :: Linux
Classifier: License :: OSI Approved :: MIT License
Classifier: Intended Audience :: Developers
Classifier: Programming Language :: Python :: 2.6
Classifier: Programming Language :: Python :: 2.7
Classifier: Programming Language :: Python :: 3
Classifier: Topic :: Software Development
Classifier: Topic :: System :: Hardware
